setup.py
bin/pwm_calibrate
pwm_calibrate/__init__.py
pwm_calibrate.egg-info/PKG-INFO
pwm_calibrate.egg-info/SOURCES.txt
pwm_calibrate.egg-info/dependency_links.txt
pwm_calibrate.egg-info/not-zip-safe
pwm_calibrate.egg-info/requires.txt
pwm_calibrate.egg-info/top_level.txt