Metadata-Version: 1.0
Name: pwm-calibrate
Version: 0.4
Summary: Provides PWM calibration tools for use on the Raspberry Pi
Home-page: http://github.com/sbma44/pwm_calibrate
Author: Tom Lee
Author-email: thomas.j.lee@gmail.com
License: MIT
Platform: UNKNOWN
